finance/__init__.py
finance/urls.py
finance/views.py
finance/views_util.py
sense_finance/__init__.py
sense_finance/settings.py
sense_finance/urls.py
sense_finance/wsgi.py
sense_finance/finance/__init__.py
sense_finance/finance/urls.py
sense_finance/finance/views.py
sense_finance/finance/views_util.py
sense_finance/finance/common/__init__.py
sense_finance/finance/common/constant0.py
sense_finance/finance/common/constant_base.py
sense_finance/finance/common/constant_custom_monit.py
sense_finance/finance/common/constant_custom_target.py
sense_finance/finance/common/constants.py
sense_finance/finance/common/daily_base.py
sense_finance/finance/common/data.py
sense_finance/finance/common/db_router.py
sense_finance/finance/common/express.py
sense_finance/finance/common/redis_store.py
sense_finance/finance/common/utils.py
sense_finance/finance/custom/__init__.py
sense_finance/finance/custom/common.py
sense_finance/finance/custom/compute_industry.py
sense_finance/finance/custom/compute_value.py
sense_finance/finance/custom/core.py
sense_finance/finance/custom/new_compute.py
sense_finance/finance/custom/new_parse.py
sense_finance/finance/custom/new_test.py
sense_finance/finance/custom/new_update.py
sense_finance/finance/custom/record_push.py
sense_finance/finance/dao/__init__.py
sense_finance/finance/dao/company.py
sense_finance/finance/dao/industry.py
sense_finance/finance/dao/report_data.py
sense_finance/finance/dao/target.py
sense_finance/finance/dao/target_data.py
sense_finance/finance/helper/__init__.py
sense_finance/finance/helper/base.py
sense_finance/finance/helper/common.py
sense_finance/finance/helper/condition.py
sense_finance/finance/job/__init__.py
sense_finance/finance/job/daily_custom_target.py
sense_finance/finance/job/daily_industry_target.py
sense_finance/finance/job/daily_latest_data.py
sense_finance/finance/job/sync_finance.py
sense_finance/finance/model/__init__.py
sense_finance/finance/model/base.py
sense_finance/finance/model/company.py
sense_finance-0.0.2.dist-info/METADATA
sense_finance-0.0.2.dist-info/WHEEL
sense_finance-0.0.2.dist-info/top_level.txt
sense_finance-0.0.2.dist-info/RECORD
